flake8_assert_check/__init__.py
flake8_assert_check-0.1.1.dist-info/entry_points.txt
flake8_assert_check-0.1.1.dist-info/WHEEL
flake8_assert_check-0.1.1.dist-info/METADATA
flake8_assert_check-0.1.1.dist-info/RECORD
